MANIFEST.in
README.md
example.py
ez_setup.py
setup.py
redditnlp/__init__.py
redditnlp.egg-info/PKG-INFO
redditnlp.egg-info/SOURCES.txt
redditnlp.egg-info/dependency_links.txt
redditnlp.egg-info/requires.txt
redditnlp.egg-info/top_level.txt
redditnlp/words/stopwords_english.txt
redditnlp/words/swearwords_english.txt