Metadata-Version: 1.1
Name: redditnlp
Version: 0.1.3
Summary: A tool to perform natural language processing of reddit content.
Home-page: https://github.com/jaijuneja/reddit-nlp
Author: Jai Juneja
Author-email: jai.juneja@gmail.com
License: BSD
Keywords: reddit,natural language processing,machine learning
Platform: UNKNOWN
Classifier: Development Status :: 3 - Alpha
Classifier: Topic :: Scientific/Engineering :: Artificial Intelligence
Classifier: Intended Audience :: Developers
Classifier: License :: OSI Approved :: BSD License
Classifier: Operating System :: OS Independent
Classifier: Programming Language :: Python
